prelim_eda_helper/__init__.py
prelim_eda_helper/prelim_eda_helper.py
prelim_eda_helper-0.1.8.dist-info/METADATA
prelim_eda_helper-0.1.8.dist-info/WHEEL
prelim_eda_helper-0.1.8.dist-info/LICENSE
prelim_eda_helper-0.1.8.dist-info/RECORD
