Metadata-Version: 2.1
Name: prelim-eda-helper
Version: 0.1.8
Summary: A preliminary EDA helper.
License: MIT
Author: Mehwish, Man Fung Morris CHAN, Xinru LU, Austin SHIH
Requires-Python: >=3.9,<3.12
Classifier: License :: OSI Approved :: MIT License
Classifier: Programming Language :: Python :: 3
Classifier: Programming Language :: Python :: 3.9
Classifier: Programming Language :: Python :: 3.10
Classifier: Programming Language :: Python :: 3.11
Requires-Dist: altair (>=4.2.0)
Requires-Dist: altair-data-server (>=0.4.1,<0.5.0)
Requires-Dist: numpy (>=1.24.1,<2.0.0)
Requires-Dist: palmerpenguins (>=0.1.4,<0.2.0)
Requires-Dist: pandas (>=1.5.2,<2.0.0)
Requires-Dist: python-semantic-release (>=7.33.0,<8.0.0)
Requires-Dist: scipy (>=1.10.0,<2.0.0)
Requires-Dist: statistics (>=1.0.3.5,<2.0.0.0)
Requires-Dist: tabulate (>=0.9.0,<0.10.0)
